pytest_datadir_ng.py
pytest_datadir_ng-1.1.1.dist-info/LICENSE
pytest_datadir_ng-1.1.1.dist-info/METADATA
pytest_datadir_ng-1.1.1.dist-info/WHEEL
pytest_datadir_ng-1.1.1.dist-info/entry_points.txt
pytest_datadir_ng-1.1.1.dist-info/top_level.txt
pytest_datadir_ng-1.1.1.dist-info/RECORD
