Metadata-Version: 2.1
Name: pytest-datadir-ng
Version: 1.1.1
Summary: Fixtures for pytest allowing test functions/methods to easily retrieve test resources from the local filesystem.
Home-page: https://github.com/Tblue/pytest-datadir-ng
Author: Tilman Blumenbach
Author-email: tilman+pypi@ax86.net
License: BSD 3-Clause License
Keywords: py.test resources files data directory directories
Platform: UNKNOWN
Classifier: Development Status :: 5 - Production/Stable
Classifier: Intended Audience :: Developers
Classifier: License :: OSI Approved :: BSD License
Classifier: Operating System :: MacOS :: MacOS X
Classifier: Operating System :: Microsoft :: Windows
Classifier: Operating System :: POSIX
Classifier: Programming Language :: Python :: 2
Classifier: Programming Language :: Python :: 2.6
Classifier: Programming Language :: Python :: 2.7
Classifier: Programming Language :: Python :: 3
Classifier: Programming Language :: Python :: 3.2
Classifier: Programming Language :: Python :: 3.3
Classifier: Programming Language :: Python :: 3.4
Classifier: Programming Language :: Python :: 3.5
Classifier: Topic :: Software Development :: Testing
Requires-Dist: pytest
